nndp/__init__.py
nndp/agnostic/__init__.py
nndp/agnostic/analysis.py
nndp/agnostic/model.py
nndp/agnostic/policy.py
nndp/agnostic/samplers.py
nndp/agnostic/train.py
nndp/core/__init__.py
nndp/core/neural_network.py
nndp/core/train.py
nndp-0.1.0.dist-info/LICENSE
nndp-0.1.0.dist-info/METADATA
nndp-0.1.0.dist-info/WHEEL
nndp-0.1.0.dist-info/top_level.txt
nndp-0.1.0.dist-info/RECORD
