Metadata-Version: 2.1
Name: nndp
Version: 0.1.0
Summary: Dynamic Programming using Neural Networks
Author-email: Marc de la Barrera <marc.delabarrera@gmail.com>, Tim de Silva <tdesilva@mit.edu>
License: The MIT License (MIT)
Keywords: economics
Requires-Python: >=3.9
License-File: LICENSE
Requires-Dist: numpy >=1.20.0
Requires-Dist: jax >=0.3.22
Requires-Dist: optax >=0.1.0
Requires-Dist: jaxlib >=0.3.22
Requires-Dist: dm-haiku >=0.0.9
Provides-Extra: doc
Requires-Dist: sphinx ~=4.2.0 ; extra == 'doc'
Requires-Dist: myst-parser ; extra == 'doc'
Requires-Dist: furo ; extra == 'doc'
